testtcwiek/__init__.py
testtcwiek/m_mod_tcwiek.py
testtcwiek-0.0.1.dist-info/LICENSE.txt
testtcwiek-0.0.1.dist-info/METADATA
testtcwiek-0.0.1.dist-info/WHEEL
testtcwiek-0.0.1.dist-info/top_level.txt
testtcwiek-0.0.1.dist-info/RECORD
