Metadata-Version: 2.1
Name: testtcwiek
Version: 0.0.1
Summary: My test package
Author-email: TC <tomas185@o2.pl>
License: MIT License
Keywords: testtcwiek,name,surname,fun function
Classifier: Framework :: IDLE
Classifier: Natural Language :: Polish
Requires-Python: >=3.0
License-File: LICENSE.txt
Requires-Dist: Python-version (>='3.0')
Requires-Dist: numpy
